README.rst
setup.py
PFlowC/__init__.py
PFlowC/__version__.py
PFlowC/geo_proxy.py
PFlowC/main.py
PFlowC/proxy.py
PFlowC.egg-info/PKG-INFO
PFlowC.egg-info/SOURCES.txt
PFlowC.egg-info/dependency_links.txt
PFlowC.egg-info/entry_points.txt
PFlowC.egg-info/requires.txt
PFlowC.egg-info/top_level.txt
PFlowC/proxy_helper/__init__.py
PFlowC/proxy_helper/macosx.py
PFlowC/utils/Country.mmdb
PFlowC/utils/__init__.py
PFlowC/utils/logger.py
PFlowC/utils/net.py
tests/test-agent-service.py
tests/test-api.py
tests/test-banner.py
tests/test-dns-socket.py
tests/test-dnspython.py
tests/test-file-path.py
tests/test-filter-domains.py
tests/test-json-dump.py
tests/test-judge-region.py
tests/test-salary.py