Metadata-Version: 2.1
Name: PFlowC
Version: 2.5.1
Summary: A net flow pilot in order to handle some proxy configuration automatically.
Home-page: https://flow-pilot.0p.fit
Author: BlackHaoke
Author-email: Haoke98@outlook.com
License: MIT
Keywords: proxy flow control
Classifier: Development Status :: 5 - Production/Stable
Classifier: Environment :: Console
Classifier: Intended Audience :: Developers
Classifier: Intended Audience :: Information Technology
Classifier: Intended Audience :: Education
Classifier: Intended Audience :: Science/Research
Classifier: License :: OSI Approved :: MIT License
Classifier: Natural Language :: English
Classifier: Operating System :: OS Independent
Classifier: Topic :: Scientific/Engineering :: Visualization
Classifier: Programming Language :: Python :: 3.6
Classifier: Programming Language :: Python :: 3.7
Classifier: Programming Language :: Python :: 3.8
Requires-Python: >=3.7
Requires-Dist: colorlog
Requires-Dist: click
Requires-Dist: mitmproxy>=10.3.0
Requires-Dist: geoip2>=4.8.0
Requires-Dist: dnspython>=2.6.1
